{"symbol": "ANGELONE", "timeframe": "1y", "window_days": 365, "target_horizon": "12M", "moneycontrol": null, "et_markets": null, "tickertape": null, "trendlyne": {"source_url": "https://trendlyne.com/equity/300864/ANGELONE/angel-one-ltd/", "reports_in_window": 3, "lookback_days": 365, "analysts": 1, "reco_raw": {"Buy": 3}, "target_price": 2333.33, "target_low": 400.0, "target_high": 3400.0, "latest_date": "2026-04-16", "buy": 3}, "yfinance": {"rating_mean": 1.73, "analysts": 11, "key": "buy", "target_mean": 314.45, "target_high": 360.0, "target_low": 262.5, "as_of": "2026-04-18"}, "yfinance_history": null, "news_activity": null, "composite": {"rating": 1.86, "label": "STRONG BUY", "inputs": 2, "target_avg": 1807.22}, "sources_used": ["trendlyne", "yfinance"], "_gh_updated": "2026-06-11T14:40:49.895574+00:00"}