{"symbol": "BHEL", "timeframe": "1y", "window_days": 365, "target_horizon": "12M", "moneycontrol": null, "et_markets": null, "tickertape": {"source_url": "https://www.tickertape.in/stocks/bharat-heavy-electricals-BHEL", "analysts": 15, "buy": 8, "hold": 7, "perc_buy": 53.3, "as_of": "2026-04-17"}, "trendlyne": {"source_url": "https://trendlyne.com/equity/189/BHEL/bharat-heavy-electricals-ltd/", "reports_in_window": 5, "lookback_days": 365, "analysts": 4, "reco_raw": {"Buy": 4, "Hold": 1}, "target_price": 320.4, "target_low": 250.0, "target_high": 370.0, "avg_upside_pct": 20.49, "latest_date": "2026-01-19", "earliest_date": "2025-10-29", "buy": 4, "hold": 1}, "yfinance": null, "yfinance_history": null, "news_activity": null, "composite": {"rating": 2.33, "label": "BUY", "inputs": 2, "target_avg": 320.4}, "sources_used": ["tickertape", "trendlyne"]}