{"symbol": "TVSMOTOR", "timeframe": "1y", "window_days": 365, "target_horizon": "12M", "moneycontrol": null, "et_markets": null, "tickertape": {"source_url": "https://www.tickertape.in/stocks/tvs-motor-company-TVSM", "analysts": 35, "buy": 27, "hold": 8, "perc_buy": 77.1, "as_of": "2026-04-17"}, "trendlyne": {"source_url": "https://trendlyne.com/equity/1430/TVSMOTOR/tvs-motor-company-ltd/", "reports_in_window": 5, "lookback_days": 365, "analysts": 4, "reco_raw": {"Buy": 4, "Hold": 1}, "target_price": 4248.4, "target_low": 3562.0, "target_high": 4554.0, "avg_upside_pct": 13.81, "latest_date": "2026-01-28", "earliest_date": "2026-01-01", "buy": 4, "hold": 1}, "yfinance": null, "yfinance_history": null, "news_activity": null, "composite": {"rating": 2.21, "label": "BUY", "inputs": 2, "target_avg": 4248.4}, "sources_used": ["tickertape", "trendlyne"]}